Workbook

Sheet Summary
A1: Summary — all-in price per person vs ceiling
A3: Prices before any organiser charge, at the airfare midpoint and 2 sharing. Organiser charge under Approach 2 shown separately. Every price rests on advertised or inferred figures; none is a quote.
A5: Cozumel, 6 nights (Sun 13 – Sat 19 Dec)
B6: Certified | C6: Beginner | D6: Advanced
A7: All-in per person | B7: =Cozumel!B22 -> 2201.3384 | C7: =Cozumel!C22 -> 2247.9617 | D7: =Cozumel!D22 -> 2894.3384
A8: Ceiling | B8: =Inputs!$B$15 -> 2000 | C8: =Inputs!$B$16 -> 2300 | D8: =Inputs!$B$15 -> 2000
A9: Headroom | B9: =B8-B7 -> -201.33836 | C9: =C8-C7 -> 52.038305 | D9: =D8-D7 -> -894.33836
A10: Organiser charge per head (Approach 2) at 20 / 30 / 40 | B10: =Cozumel!B65 -> 74.842105 | C10: =Cozumel!C65 -> 49.034483 | D10: =Cozumel!D65 -> 36.461538
A11: 5-night version, all-in per person | B11: =Cozumel!B46 -> 2078.3511 | C11: =Cozumel!C46 -> 2022.9745 | D11: =Cozumel!D46 -> 2771.3511
A12: Core only (excl. meals, tips, insurance), 6 nights | B12: =Cozumel!B23 -> 1822.3384 | C12: =Cozumel!C23 -> 1868.9617 | D12: =Cozumel!D23 -> 2515.3384
A14: Egypt, Marsa Shagra (Sat 2 – Sat 9 Jan)
B15: Certified | C15: Beginner | D15: Advanced
A16: All-in per person, Royal Tent, via Hurghada | B16: =January!B21 -> 2577.475 | C16: =January!C21 -> 2727.6665 | D16: =January!D21 -> 2962.699
A17: All-in per person, Deluxe Chalet, via Marsa Alam | B17: =January!B43 -> 2774.673 | C17: =January!C43 -> 2924.8645 | D17: =January!D43 -> 3159.897
A18: Ceiling | B18: =Inputs!$B$17 -> 2700 | C18: =Inputs!$B$17 -> 2700 | D18: =Inputs!$B$17 -> 2700
A19: Headroom (Royal Tent) | B19: =B18-B16 -> 122.525 | C19: =C18-C16 -> -27.6665 | D19: =D18-D16 -> -262.699
A20: Organiser charge per head (Approach 2) at 15 / 20 / 25 | B20: =January!B63 -> 110.64746 | C20: =January!C63 -> 81.529711 | D20: =January!D63 -> 64.544354
A21: Core only (excl. incidentals, tips, insurance), Royal Tent | B21: =January!B22 -> 2318.475 | C21: =January!C22 -> 2468.6665 | D21: =January!D22 -> 2703.699
A23: Thanksgiving (10 people)
B24: 25–29 Nov | C24: 19–24 Nov
A25: Puerto Rico, all-in per person | B25: =Thanksgiving!C18 -> 1720 | C25: =Thanksgiving!C35 -> 1988
A26: Tiger Beach, all-in per person | B26: =Thanksgiving!C51 -> 2366.8 | C26: =Thanksgiving!C69 -> 2980.7
A27: Ceiling | B27: =Inputs!$B$14 -> 1500 | C27: =Inputs!$B$14 -> 1500
A28: Puerto Rico headroom | B28: =B27-B25 -> -220 | C28: =C27-C25 -> -488
A29: Tiger Beach extra vs Puerto Rico | B29: =B26-B25 -> 646.8 | C29: =C26-C25 -> 992.7
A30: Puerto Rico core only (excl. meals, tips, insurance) | B30: =Thanksgiving!C19 -> 1411 | C30: =Thanksgiving!C36 -> 1644

Sheet Inputs
A1: Inputs — Wharton Outdoors Club dive trips 2026–27
A3: Blue cells are inputs; every other sheet reads from here. Flags: ADVERTISED (snippet) = seen on the named source; QUOTE NEEDED = unverified lead; INFERRED = our estimate. Sources are listed in pricing/sources.csv.
A5: Exchange rates (mid-market, 21 Sep 2026)
A6: USD per EUR 1 | B6: 1.1465 | C6: USD/EUR | D6: ADVERTISED (snippet)
A7: MXN per USD 1 | B7: 17.23 | C7: MXN/USD | D7: ADVERTISED (snippet)
A9: Group composition
A10: Beginner share of group (Cozumel, Egypt) | B10: 0.5 | C10: share | D10: brief
A11: Advanced share of group | B11: 0.15 | C11: share | D11: brief
A13: Budget ceilings (all-in incl. flights, per person)
A14: Thanksgiving | B14: 1500 | C14: USD | D14: brief
A15: Cozumel — certified | B15: 2000 | C15: USD | D15: brief
A16: Cozumel — beginner | B16: 2300 | C16: USD | D16: brief
A17: Egypt | B17: 2700 | C17: USD | D17: brief
A19: Shared allowances
A20: Dive-accident insurance (DAN membership + Preferred plan, annual) | B20: 119 | C20: USD | D20: ADVERTISED (snippet)
A21: Meals and incidentals per day where not on full board | B21: 35 | C21: USD/day | D21: INFERRED
A22: Tips and local extras per trip | B22: 50 | C22: USD | D22: INFERRED
A24: Cozumel, Sun 13 – Sat 19 Dec 2026 (6 nights, confirmed 22 Sep) and 5-night variant
A25: Flight PHL–CZM return, low | B25: 568 | C25: USD | D25: ADVERTISED (snippet, aggregator)
A26: Flight PHL–CZM return, high | B26: 800 | C26: USD | D26: ADVERTISED (snippet, aggregator)
A27: Alternative: PHL–CUN + ADO bus + ferry, all-in return | B27: 400 | C27: USD | D27: ADVERTISED (snippet); mid of 315–450
A28: CZM airport shared van, each way | B28: 15 | C28: USD | D28: ADVERTISED (snippet)
A29: Hotel Cozumel & Resort, pp/night, 2 sharing, breakfast incl. | B29: 54 | C29: USD | D29: ADVERTISED (snippet); upper of 41–54
A30: Hotel Cozumel & Resort, pp/night, 3 sharing | B30: 40 | C30: USD | D30: INFERRED (30–40)
A31: Casa Mexicana, pp/night, 2 sharing, breakfast incl. | B31: 84 | C31: USD | D31: ADVERTISED (snippet); upper of 65–84
A32: Nights, 6-night version (Sun 13 – Sat 19) | B32: 6 | C32: nights | D32: dates confirmed 22 Sep
A33: Nights, 5-night version | B33: 5 | C33: nights | D33: brief
A34: PADI Open Water in-water course, gear, wetsuit and DAN training cover incl. (Sand Dollar) | B34: 350 | C34: USD | D34: QUOTED 2026-09-22 (Sand Dollar email); Blue Note advertised 400
A35: PADI Open Water eLearning, bought from PADI | B35: 195 | C35: USD | D35: ADVERTISED (snippet); 195–230
A36: 5-day / 10-dive package (Blue Note), MXN price | B36: 10500 | C36: MXN | D36: ADVERTISED (snippet); USD 600 listed
... A50: Operator free places: one per N paying (diving only) | B50: 10 | C50: paying | D50: QUOTED 2026-09-22: Aldora 1 comp at 10+ paid; Sand Dollar one free diver
A52: Egypt (Marsa Shagra), Sat 2 – Sat 9 Jan 2027, 6 nights on the ground
A53: Flight PHL–HRG return via Lufthansa Group hub, low | B53: 700 | C53: USD | D53: ADVERTISED (snippet, aggregator)
A54: Flight PHL–HRG return, high | B54: 1300 | C54: USD | D54: ADVERTISED (snippet, aggregator)
A55: Flight PHL–RMF return (thin January schedule) | B55: 1300 | C55: USD | D55: INFERRED; 1,000–1,600
A56: Open-jaw add-on: HRG–ZRH one-way instead of return leg (net of return leg) | B56: 0 | C56: USD | D56: QUOTE NEEDED; one-way ~USD 550 seen
A57: Nights on the ground (Sun 3 – Sat 9) | B57: 6 | C57: nights | D57: itinerary
A58: Royal Tent, full board, pp/night sharing | B58: 78 | C58: EUR | D58: QUOTE NEEDED (brief; low season)
A59: Deluxe Chalet, full board, pp/night sharing | B59: 113 | C59: EUR | D59: QUOTE NEEDED (brief; low season)
A60: PADI Open Water incl. gear | B60: 358 | C60: EUR | D60: QUOTE NEEDED (brief)
A61: PADI e-code (waived if bought direct?) | B61: 94 | C61: EUR | D61: QUOTE NEEDED (brief)
A62: 5-day house-reef dive package | B62: 347 | C62: EUR | D62: QUOTE NEEDED (brief)
A63: Extra house-reef dive day | B63: 69 | C63: EUR | D63: QUOTE NEEDED (brief)
A64: Gear rental per day, certified divers | B64: 15 | C64: EUR | D64: INFERRED; QUOTE NEEDED
... A78: RSDS free places: threshold for second free guest | B78: 22 | C78: guests | D78: ADVERTISED (snippet); brief says 21st
A80: Thanksgiving: Puerto Rico (La Parguera) and Tiger Beach variant, 25–29 Nov or 19–24 Nov 2026
A81: Flight PHL–SJU return nonstop, low (Thanksgiving week) | B81: 400 | C81: USD | D81: INFERRED; off-peak one-way from USD 62–70 ADVERTISED
A82: Flight PHL–SJU return nonstop, high | B82: 700 | C82: USD | D82: INFERRED; QUOTE NEEDED
A83: Nights, Wed 25 – Sun 29 Nov | B83: 4 | C83: nights | D83: brief
A84: Nights, Thu 19 – Tue 24 Nov | B84: 5 | C84: nights | D84: brief
A85: La Parguera hotel, pp/night, 2 sharing (Parador Villa Parguera USD 135–170/room) | B85: 75 | C85: USD | D85: ADVERTISED (snippet, aggregator)
A86: La Parguera hotel, pp/night, 3 sharing | B86: 50 | C86: USD | D86: INFERRED
A87: Two-tank Wall dive (Paradise Scuba): USD 145 less 15% group discount, plus 11.5% tax; own gear | B87: 137 | C87: USD | D87: QUOTED 2026-09-22 price and discount; tax rate INFERRED (PR IVU), QUOTE NEEDED
A88: Desecheo two-tank incl. USD 20 park fee, own gear (Taino Divers has no boat as of 2026-09-23; Island Style Charters, max 4 divers per charter, is the referral) | B88: 140 | C88: USD | D88: ADVERTISED (snippet, aggregator lead); QUOTE NEEDED
A89: Dive days, 25–29 Nov (Thu–Sat; Sat last dive by noon) | B89: 3 | C89: days | D89: itinerary
A90: Dive days, 19–24 Nov (Fri–Mon) | B90: 4 | C90: days | D90: itinerary
A91: Of which Desecheo days (weather permitting) | B91: 1 | C91: days | D91: itinerary
A92: Bio bay boat tour (Parguera Eco Tours; Paradise Scuba also offers, price pending) | B92: 45 | C92: USD | D92: ADVERTISED (snippet)
... A106: Full 5 mm wetsuit rental if needed, per day | B106: 15 | C106: USD | D106: INFERRED
A108: Organiser place
A109: George is costed as a diving participant. Free places from operators are applied first; any remainder is shown as a disclosed per-head charge.

Sheet Cozumel
A1: Cozumel — Sun 13 – Sat 19 Dec 2026 (6 nights, confirmed 22 Sep) and 5-night variant
A3: All figures per person, USD. Reads from Inputs. Lodging at Hotel Cozumel & Resort, 2 sharing, breakfast included. Flights at the midpoint of the aggregator band.
A5: A. Per-person cost, 6-night version (no spare day: a norther on Sat/Sun hits the certification dives)
A6: Item | B6: Certified | C6: Beginner | D6: Advanced
A7: Flight PHL–CZM return (band midpoint) | B7: =AVERAGE(Inputs!$B$25,Inputs!$B$26) -> 684 | C7: =AVERAGE(Inputs!$B$25,Inputs!$B$26) -> 684 | D7: =AVERAGE(Inputs!$B$25,Inputs!$B$26) -> 684
A8: Airport transfers | B8: =2*Inputs!$B$28 -> 30 | C8: =2*Inputs!$B$28 -> 30 | D8: =2*Inputs!$B$28 -> 30
A9: Lodging, 2 sharing, breakfast included | B9: =Inputs!$B$32*Inputs!$B$29 -> 324 | C9: =Inputs!$B$32*Inputs!$B$29 -> 324 | D9: =Inputs!$B$32*Inputs!$B$29 -> 324
A10: Open Water in-water course (gear included) | B10: 0 | C10: =Inputs!$B$34 -> 350 | D10: 0
A11: PADI eLearning | B11: 0 | C11: =Inputs!$B$35 -> 195 | D11: 0
A12: Boat diving (package for certified; fun days for beginners) | B12: =Inputs!$B$36/Inputs!$B$7 -> 609.40221 | C12: =Inputs!$B$47*Inputs!$B$37 -> 204 | D12: =Inputs!$B$36/Inputs!$B$7 -> 609.40221
A13: Advanced Open Water course | B13: 0 | C13: 0 | D13: =Inputs!$B$41 -> 530
A14: Marine park fee | B14: =Inputs!$B$45*Inputs!$B$38/Inputs!$B$7 -> 69.936158 | C14: =(Inputs!$B$49+Inputs!$B$47)*Inputs!$B$38/Inputs!$B$7 -> 41.961695 | D14: =Inputs!$B$45*Inputs!$B$38/Inputs!$B$7 -> 69.936158
A15: Gear rental | B15: =Inputs!$B$45*Inputs!$B$39 -> 100 | C15: =Inputs!$B$47*Inputs!$B$39 -> 40 | D15: =Inputs!$B$45*Inputs!$B$39 -> 100
A16: Refresher (if >12 months since last dive) | B16: =Inputs!$B$40 -> 5 | C16: 0 | D16: =Inputs!$B$40 -> 5
A17: Nitrox fills (advanced, 6 tanks) | B17: 0 | C17: 0 | D17: =6*Inputs!$B$42 -> 78
A18: Night dive (advanced) | B18: 0 | C18: 0 | D18: =Inputs!$B$43 -> 85
A19: Meals and incidentals | B19: =Inputs!$B$32*Inputs!$B$21 -> 210 | C19: =Inputs!$B$32*Inputs!$B$21 -> 210 | D19: =Inputs!$B$32*Inputs!$B$21 -> 210
A20: Tips and local extras | B20: =Inputs!$B$22 -> 50 | C20: =Inputs!$B$22 -> 50 | D20: =Inputs!$B$22 -> 50
A21: Dive-accident insurance | B21: =Inputs!$B$20 -> 119 | C21: =Inputs!$B$20 -> 119 | D21: =Inputs!$B$20 -> 119
A22: Total per person | B22: =SUM(B7:B21) -> 2201.3384 | C22: =SUM(C7:C21) -> 2247.9617 | D22: =SUM(D7:D21) -> 2894.3384
A23: of which core: flights, transfers, lodging, diving, fees (excl. meals, tips, insurance) | B23: =B22-SUM(B19:B21) -> 1822.3384 | C23: =C22-SUM(C19:C21) -> 1868.9617 | D23: =D22-SUM(D19:D21) -> 2515.3384
A24: Budget ceiling | B24: =Inputs!$B$15 -> 2000 | C24: =Inputs!$B$16 -> 2300 | D24: =Inputs!$B$15 -> 2000
A25: Headroom (negative = over ceiling) | B25: =B24-B22 -> -201.33836 | C25: =C24-C22 -> 52.038305 | D25: =D24-D22 -> -894.33836
A26: Optional bull-shark day, Playa del Carmen (BAITED), not in total | B26: =Inputs!$B$44 -> 260 | C26: =Inputs!$B$44 -> 260 | D26: =Inputs!$B$44 -> 260
A29: B. Per-person cost, 5-night version (Sun 13 return; no norther buffer)
A30: Item | B30: Certified | C30: Beginner | D30: Advanced
A31: Flight PHL–CZM return (band midpoint) | B31: =AVERAGE(Inputs!$B$25,Inputs!$B$26) -> 684 | C31: =AVERAGE(Inputs!$B$25,Inputs!$B$26) -> 684 | D31: =AVERAGE(Inputs!$B$25,Inputs!$B$26) -> 684
A32: Airport transfers | B32: =2*Inputs!$B$28 -> 30 | C32: =2*Inputs!$B$28 -> 30 | D32: =2*Inputs!$B$28 -> 30
A33: Lodging, 2 sharing, breakfast included | B33: =Inputs!$B$33*Inputs!$B$29 -> 270 | C33: =Inputs!$B$33*Inputs!$B$29 -> 270 | D33: =Inputs!$B$33*Inputs!$B$29 -> 270
A34: Open Water in-water course (gear included) | B34: 0 | C34: =Inputs!$B$34 -> 350 | D34: 0
A35: PADI eLearning | B35: 0 | C35: =Inputs!$B$35 -> 195 | D35: 0
A36: Boat diving (package for certified; fun days for beginners) | B36: =Inputs!$B$36/Inputs!$B$7 -> 609.40221 | C36: =Inputs!$B$48*Inputs!$B$37 -> 102 | D36: =Inputs!$B$36/Inputs!$B$7 -> 609.40221
A37: Advanced Open Water course | B37: 0 | C37: 0 | D37: =Inputs!$B$41 -> 530
A38: Marine park fee | B38: =Inputs!$B$46*Inputs!$B$38/Inputs!$B$7 -> 55.948926 | C38: =(Inputs!$B$49+Inputs!$B$48)*Inputs!$B$38/Inputs!$B$7 -> 27.974463 | D38: =Inputs!$B$46*Inputs!$B$38/Inputs!$B$7 -> 55.948926
A39: Gear rental | B39: =Inputs!$B$46*Inputs!$B$39 -> 80 | C39: =Inputs!$B$48*Inputs!$B$39 -> 20 | D39: =Inputs!$B$46*Inputs!$B$39 -> 80
A40: Refresher (if >12 months since last dive) | B40: =Inputs!$B$40 -> 5 | C40: 0 | D40: =Inputs!$B$40 -> 5
A41: Nitrox fills (advanced, 6 tanks) | B41: 0 | C41: 0 | D41: =6*Inputs!$B$42 -> 78
A42: Night dive (advanced) | B42: 0 | C42: 0 | D42: =Inputs!$B$43 -> 85
A43: Meals and incidentals | B43: =Inputs!$B$33*Inputs!$B$21 -> 175 | C43: =Inputs!$B$33*Inputs!$B$21 -> 175 | D43: =Inputs!$B$33*Inputs!$B$21 -> 175
A44: Tips and local extras | B44: =Inputs!$B$22 -> 50 | C44: =Inputs!$B$22 -> 50 | D44: =Inputs!$B$22 -> 50
A45: Dive-accident insurance | B45: =Inputs!$B$20 -> 119 | C45: =Inputs!$B$20 -> 119 | D45: =Inputs!$B$20 -> 119
A46: Total per person | B46: =SUM(B31:B45) -> 2078.3511 | C46: =SUM(C31:C45) -> 2022.9745 | D46: =SUM(D31:D45) -> 2771.3511
A47: of which core: flights, transfers, lodging, diving, fees (excl. meals, tips, insurance) | B47: =B46-SUM(B43:B45) -> 1734.3511 | C47: =C46-SUM(C43:C45) -> 1678.9745 | D47: =D46-SUM(D43:D45) -> 2427.3511
A48: Budget ceiling | B48: =Inputs!$B$15 -> 2000 | C48: =Inputs!$B$16 -> 2300 | D48: =Inputs!$B$15 -> 2000
A49: Headroom (negative = over ceiling) | B49: =B48-B46 -> -78.351132 | C49: =C48-C46 -> 277.02554 | D49: =D48-D46 -> -771.35113
A52: C. Organiser place (6-night version), by group size
B53: 20 people | C53: 30 people | D53: 40 people
A54: Group size incl. George | B54: 20 | C54: 30 | D54: 40
A55: Paying participants | B55: =B54-1 -> 19 | C55: =C54-1 -> 29 | D55: =D54-1 -> 39
A56: Operator free places earned (one per N paying, QUOTE NEEDED) | B56: =INT(B55/Inputs!$B$50) -> 1 | C56: =INT(C55/Inputs!$B$50) -> 2 | D56: =INT(D55/Inputs!$B$50) -> 3
A57: Value of one free place (diving, park fee, gear) | B57: =B12+B14+B15 -> 779.33836 | C57: =B12+B14+B15 -> 779.33836 | D57: =B12+B14+B15 -> 779.33836
A58: George's all-in cost (certified column) | B58: =B22 -> 2201.3384 | C58: =B22 -> 2201.3384 | D58: =B22 -> 2201.3384
A59: Covered by free places (max one place used for George) | B59: =MIN(B56,1)*B57 -> 779.33836 | C59: =MIN(C56,1)*C57 -> 779.33836 | D59: =MIN(D56,1)*D57 -> 779.33836
A61: Approach 1 — free places only
A62: George pays himself | B62: =B58-B59 -> 1422 | C62: =C58-C59 -> 1422 | D62: =D58-D59 -> 1422
A63: Per-head charge to participants | B63: 0 | C63: 0 | D63: 0
A64: Approach 2 — free places plus disclosed per-head charge
A65: Per-head charge to participants | B65: =(B58-B59)/B55 -> 74.842105 | C65: =(C58-C59)/C55 -> 49.034483 | D65: =(D58-D59)/D55 -> 36.461538
A66: Certified all-in with charge | B66: =B22+B65 -> 2276.1805 | C66: =B22+C65 -> 2250.3728 | D66: =B22+D65 -> 2237.7999
A67: Beginner all-in with charge | B67: =C22+B65 -> 2322.8038 | C67: =C22+C65 -> 2296.9962 | D67: =C22+D65 -> 2284.4232
A68: Approach 3 — per-head charge only (no free places)
A69: Per-head charge to participants | B69: =B58/B55 -> 115.85991 | C69: =B58/C55 -> 75.908219 | D69: =B58/D55 -> 56.444573
A70: Certified all-in with charge | B70: =B22+B69 -> 2317.1983 | C70: =B22+C69 -> 2277.2466 | D70: =B22+D69 -> 2257.7829
A71: Beginner all-in with charge | B71: =C22+B69 -> 2363.8216 | C71: =C22+C69 -> 2323.8699 | D71: =C22+D69 -> 2304.4063
A72: Unused free places (could offset an instructor or assistant place) | B72: =MAX(B56-1,0) -> 0 | C72: =MAX(C56-1,0) -> 1 | D72: =MAX(D56-1,0) -> 2
A75: D. Sensitivity (6-night version, per person, before organiser charge)
A76: Airfare | B76: Low | C76: Midpoint | D76: High
A77: Fare used | B77: =Inputs!$B$25 -> 568 | C77: =AVERAGE(Inputs!$B$25,Inputs!$B$26) -> 684 | D77: =Inputs!$B$26 -> 800
A78: Certified total | B78: =B22-B7+B77 -> 2085.3384 | C78: =B22-B7+C77 -> 2201.3384 | D78: =B22-B7+D77 -> 2317.3384
A79: Beginner total | B79: =C22-B7+B77 -> 2131.9617 | C79: =C22-B7+C77 -> 2247.9617 | D79: =C22-B7+D77 -> 2363.9617
A80: Cancún + ferry routing instead (certified) | B80: =B22-B7+Inputs!$B$27 -> 1917.3384
A82: MXN per USD | B82: Peso 10% stronger | C82: Rate used | D82: Peso 10% weaker
A83: Rate | B83: =Inputs!$B$7*0.9 -> 15.507 | C83: =Inputs!$B$7 -> 17.23 | D83: =Inputs!$B$7*1.1 -> 18.953
A84: MXN-priced items, certified (package + park fee), in MXN | B84: =Inputs!$B$36+Inputs!$B$45*Inputs!$B$38 -> 11705 | C84: =Inputs!$B$36+Inputs!$B$45*Inputs!$B$38 -> 11705 | D84: =Inputs!$B$36+Inputs!$B$45*Inputs!$B$38 -> 11705
A85: Certified total at that rate | B85: =B22-B12-B14+B84/B83 -> 2276.8204 | C85: =B22-B12-B14+C84/C83 -> 2201.3384 | D85: =B22-B12-B14+D84/D83 -> 2139.5803
A86: Beginner: only the park fee is MXN-priced; effect under USD 10 per person either way
A89: E. Break-even group size (6-night version)
A90: Smallest group at which a certified diver stays under the ceiling when George's uncovered cost is spread per head (Approach 2, one free place assumed from 10 paying).
A91: Certified: uncovered organiser cost | B91: =B58-B57 -> 1422
A92: Certified: headroom under ceiling per person | B92: =Inputs!$B$15-B22 -> -201.33836
A93: Certified: break-even group size incl. George | B93: =IF(B92>0,ROUNDUP(B91/B92,0)+1,"not viable at this price") -> not viable at this price
A94: Beginner: headroom under ceiling per person | B94: =Inputs!$B$16-C22 -> 52.038305
A95: Beginner: break-even group size incl. George | B95: =IF(B94>0,ROUNDUP(B91/B94,0)+1,"not viable at this price") -> 29
A96: Operator minimum for a private course block: QUOTE NEEDED (PADI ratio 8 students per instructor on open-water dives).
A99: F. Deposit schedule (draft, matched to advertised terms; all QUOTE NEEDED)
A100: Milestone | B100: Date | C100: Amount per person | D100: Basis
A101: Participant deposit to club (Aruba 2024 precedent USD 575) | B101: Fri 9 Oct 2026 | C101: 600 | D101: Covers operator and hotel deposits below
A102: Dive operator deposit (Sand Dollar: 25% of package; Blue Note: size QUOTE NEEDED) | B102: Fri 16 Oct 2026 | C102: =0.25*B12 -> 152.35055 | D102: 25% of diving
A103: Hotel block deposit (typically one night per room) | B103: Fri 16 Oct 2026 | C103: =Inputs!$B$29 -> 54 | D103: One night, 2 sharing
A104: Airline group deposit (AA Group & Meeting Travel, per passenger, amount QUOTE NEEDED) | B104: Fri 2 Oct 2026 | C104: unknown | D104: Space held without names; names 48 h out
A105: Balance to club | B105: Fri 6 Nov 2026 | C105: =B22-600 -> 1601.3384 | D105: Certified all-in less deposit
A106: Last day for full operator refund (Blue Magic group terms: 60 days, less 5%) | B106: Fri 9 Oct 2026 | D106: Blue Magic policy page (snippet)
A107: Blue Magic 50% refund window closes | B107: Sun 8 Nov 2026 | D107: 45–30 days before arrival
A108: Blue Note / Aldora / Sand Dollar: free cancellation to 48 h before | B108: Sun 6 Dec 2026 | D108: Per policy snippets

Sheet January
A1: Egypt, Marsa Shagra — Sat 2 – Sat 9 Jan 2027 (6 nights on the ground)
A3: All figures per person, USD, converted from EUR at the Inputs rate. Full board included in lodging. Flights PHL–HRG via a Lufthansa Group hub at the band midpoint; transfers from Hurghada (3 h) unless RMF proves bookable.
A5: A. Per-person cost, Royal Tent, transfers from Hurghada (10–20 people)
A6: Item | B6: Certified | C6: Beginner | D6: Advanced
A7: Flight PHL–HRG return via Europe (band midpoint) | B7: =AVERAGE(Inputs!$B$53,Inputs!$B$54) -> 1000 | C7: =AVERAGE(Inputs!$B$53,Inputs!$B$54) -> 1000 | D7: =AVERAGE(Inputs!$B$53,Inputs!$B$54) -> 1000
A8: Airport transfers, both ways | B8: =2*Inputs!$B$71*Inputs!$B$6 -> 94.013 | C8: =2*Inputs!$B$71*Inputs!$B$6 -> 94.013 | D8: =2*Inputs!$B$71*Inputs!$B$6 -> 94.013
A9: Lodging, full board, 2 sharing | B9: =Inputs!$B$57*Inputs!$B$58*Inputs!$B$6 -> 536.562 | C9: =Inputs!$B$57*Inputs!$B$58*Inputs!$B$6 -> 536.562 | D9: =Inputs!$B$57*Inputs!$B$58*Inputs!$B$6 -> 536.562
A10: Open Water course incl. gear | B10: 0 | C10: =Inputs!$B$60*Inputs!$B$6 -> 410.447 | D10: 0
A11: PADI e-code | B11: 0 | C11: =Inputs!$B$61*Inputs!$B$6 -> 107.771 | D11: 0
A12: House-reef dive package (5 days) or post-course dive days | B12: =Inputs!$B$62*Inputs!$B$6 -> 397.8355 | C12: =Inputs!$B$76*Inputs!$B$63*Inputs!$B$6 -> 158.217 | D12: =Inputs!$B$62*Inputs!$B$6 -> 397.8355
A13: Advanced Open Water course | B13: 0 | C13: 0 | D13: =Inputs!$B$65*Inputs!$B$6 -> 361.1475
A14: Gear rental | B14: =Inputs!$B$75*Inputs!$B$64*Inputs!$B$6 -> 85.9875 | C14: =Inputs!$B$76*Inputs!$B$64*Inputs!$B$6 -> 34.395 | D14: =Inputs!$B$75*Inputs!$B$64*Inputs!$B$6 -> 85.9875
A15: Excursions: Dolphin House and Abu Dabab (certified); Elphinstone (advanced) | B15: =(Inputs!$B$66+Inputs!$B$67)*Inputs!$B$6 -> 144.459 | C15: =Inputs!$B$67*Inputs!$B$6 -> 67.6435 | D15: =(Inputs!$B$66+Inputs!$B$68)*Inputs!$B$6 -> 168.5355
A16: Visa and meet-and-assist | B16: =Inputs!$B$72*Inputs!$B$6 -> 51.5925 | C16: =Inputs!$B$72*Inputs!$B$6 -> 51.5925 | D16: =Inputs!$B$72*Inputs!$B$6 -> 51.5925
A17: On-site chamber fee | B17: =Inputs!$B$73*Inputs!$B$6 -> 8.0255 | C17: =Inputs!$B$73*Inputs!$B$6 -> 8.0255 | D17: =Inputs!$B$73*Inputs!$B$6 -> 8.0255
A18: Incidentals on full board | B18: =Inputs!$B$57*Inputs!$B$74 -> 90 | C18: =Inputs!$B$57*Inputs!$B$74 -> 90 | D18: =Inputs!$B$57*Inputs!$B$74 -> 90
A19: Tips and local extras | B19: =Inputs!$B$22 -> 50 | C19: =Inputs!$B$22 -> 50 | D19: =Inputs!$B$22 -> 50
A20: Dive-accident insurance | B20: =Inputs!$B$20 -> 119 | C20: =Inputs!$B$20 -> 119 | D20: =Inputs!$B$20 -> 119
A21: Total per person | B21: =SUM(B7:B20) -> 2577.475 | C21: =SUM(C7:C20) -> 2727.6665 | D21: =SUM(D7:D20) -> 2962.699
A22: of which core: flights, transfers, lodging, diving, fees (excl. meals, tips, insurance) | B22: =B21-SUM(B18:B20) -> 2318.475 | C22: =C21-SUM(C18:C20) -> 2468.6665 | D22: =D21-SUM(D18:D20) -> 2703.699
A23: Budget ceiling | B23: =Inputs!$B$17 -> 2700 | C23: =Inputs!$B$17 -> 2700 | D23: =Inputs!$B$17 -> 2700
A24: Headroom (negative = over ceiling) | B24: =B23-B21 -> 122.525 | C24: =C23-C21 -> -27.6665 | D24: =D23-D21 -> -262.699
A27: B. Per-person cost, Deluxe Chalet, transfers from Marsa Alam airport (10–20 people)
A28: Item | B28: Certified | C28: Beginner | D28: Advanced
A29: Flight PHL–HRG return via Europe (band midpoint) | B29: =AVERAGE(Inputs!$B$53,Inputs!$B$54) -> 1000 | C29: =AVERAGE(Inputs!$B$53,Inputs!$B$54) -> 1000 | D29: =AVERAGE(Inputs!$B$53,Inputs!$B$54) -> 1000
A30: Airport transfers, both ways | B30: =2*Inputs!$B$69*Inputs!$B$6 -> 50.446 | C30: =2*Inputs!$B$69*Inputs!$B$6 -> 50.446 | D30: =2*Inputs!$B$69*Inputs!$B$6 -> 50.446
A31: Lodging, full board, 2 sharing | B31: =Inputs!$B$57*Inputs!$B$59*Inputs!$B$6 -> 777.327 | C31: =Inputs!$B$57*Inputs!$B$59*Inputs!$B$6 -> 777.327 | D31: =Inputs!$B$57*Inputs!$B$59*Inputs!$B$6 -> 777.327
A32: Open Water course incl. gear | B32: 0 | C32: =Inputs!$B$60*Inputs!$B$6 -> 410.447 | D32: 0
A33: PADI e-code | B33: 0 | C33: =Inputs!$B$61*Inputs!$B$6 -> 107.771 | D33: 0
A34: House-reef dive package (5 days) or post-course dive days | B34: =Inputs!$B$62*Inputs!$B$6 -> 397.8355 | C34: =Inputs!$B$76*Inputs!$B$63*Inputs!$B$6 -> 158.217 | D34: =Inputs!$B$62*Inputs!$B$6 -> 397.8355
A35: Advanced Open Water course | B35: 0 | C35: 0 | D35: =Inputs!$B$65*Inputs!$B$6 -> 361.1475
A36: Gear rental | B36: =Inputs!$B$75*Inputs!$B$64*Inputs!$B$6 -> 85.9875 | C36: =Inputs!$B$76*Inputs!$B$64*Inputs!$B$6 -> 34.395 | D36: =Inputs!$B$75*Inputs!$B$64*Inputs!$B$6 -> 85.9875
A37: Excursions: Dolphin House and Abu Dabab (certified); Elphinstone (advanced) | B37: =(Inputs!$B$66+Inputs!$B$67)*Inputs!$B$6 -> 144.459 | C37: =Inputs!$B$67*Inputs!$B$6 -> 67.6435 | D37: =(Inputs!$B$66+Inputs!$B$68)*Inputs!$B$6 -> 168.5355
A38: Visa and meet-and-assist | B38: =Inputs!$B$72*Inputs!$B$6 -> 51.5925 | C38: =Inputs!$B$72*Inputs!$B$6 -> 51.5925 | D38: =Inputs!$B$72*Inputs!$B$6 -> 51.5925
A39: On-site chamber fee | B39: =Inputs!$B$73*Inputs!$B$6 -> 8.0255 | C39: =Inputs!$B$73*Inputs!$B$6 -> 8.0255 | D39: =Inputs!$B$73*Inputs!$B$6 -> 8.0255
A40: Incidentals on full board | B40: =Inputs!$B$57*Inputs!$B$74 -> 90 | C40: =Inputs!$B$57*Inputs!$B$74 -> 90 | D40: =Inputs!$B$57*Inputs!$B$74 -> 90
A41: Tips and local extras | B41: =Inputs!$B$22 -> 50 | C41: =Inputs!$B$22 -> 50 | D41: =Inputs!$B$22 -> 50
A42: Dive-accident insurance | B42: =Inputs!$B$20 -> 119 | C42: =Inputs!$B$20 -> 119 | D42: =Inputs!$B$20 -> 119
A43: Total per person | B43: =SUM(B29:B42) -> 2774.673 | C43: =SUM(C29:C42) -> 2924.8645 | D43: =SUM(D29:D42) -> 3159.897
A44: of which core: flights, transfers, lodging, diving, fees (excl. meals, tips, insurance) | B44: =B43-SUM(B40:B42) -> 2515.673 | C44: =C43-SUM(C40:C42) -> 2665.8645 | D44: =D43-SUM(D40:D42) -> 2900.897
A45: Budget ceiling | B45: =Inputs!$B$17 -> 2700 | C45: =Inputs!$B$17 -> 2700 | D45: =Inputs!$B$17 -> 2700
A46: Headroom (negative = over ceiling) | B46: =B45-B43 -> -74.673 | C46: =C45-C43 -> -224.8645 | D46: =D45-D43 -> -459.897
A47: Open-jaw to Zurich for Euroski (net add-on, QUOTE NEEDED) | B47: =Inputs!$B$56 -> 0 | C47: =Inputs!$B$56 -> 0 | D47: =Inputs!$B$56 -> 0
A50: C. Organiser place (Royal Tent scenario), by group size
B51: 15 people | C51: 20 people | D51: 25 people
A52: Group size incl. George | B52: 15 | C52: 20 | D52: 25
A53: Paying participants | B53: =B52-1 -> 14 | C53: =C52-1 -> 19 | D53: =D52-1 -> 24
A54: RSDS free places (1 at 11+, 2 at 22+ guests) | B54: =IF(B52>=Inputs!$B$78,2,IF(B52>=Inputs!$B$77,1,0)) -> 1 | C54: =IF(C52>=Inputs!$B$78,2,IF(C52>=Inputs!$B$77,1,0)) -> 1 | D54: =IF(D52>=Inputs!$B$78,2,IF(D52>=Inputs!$B$77,1,0)) -> 2
A55: Value of one free place (room, transfers, dive package) | B55: =B9+B8+B12 -> 1028.4105 | C55: =B9+B8+B12 -> 1028.4105 | D55: =B9+B8+B12 -> 1028.4105
A56: George's all-in cost (certified column) | B56: =B21 -> 2577.475 | C56: =B21 -> 2577.475 | D56: =B21 -> 2577.475
A57: Covered by free places (one used for George) | B57: =MIN(B54,1)*B55 -> 1028.4105 | C57: =MIN(C54,1)*C55 -> 1028.4105 | D57: =MIN(D54,1)*D55 -> 1028.4105
A59: Approach 1 — free places only
A60: George pays himself | B60: =B56-B57 -> 1549.0645 | C60: =C56-C57 -> 1549.0645 | D60: =D56-D57 -> 1549.0645
A61: Per-head charge to participants | B61: 0 | C61: 0 | D61: 0
A62: Approach 2 — free places plus disclosed per-head charge
A63: Per-head charge to participants | B63: =(B56-B57)/B53 -> 110.64746 | C63: =(C56-C57)/C53 -> 81.529711 | D63: =(D56-D57)/D53 -> 64.544354
A64: Certified all-in with charge | B64: =B21+B63 -> 2688.1225 | C64: =B21+C63 -> 2659.0047 | D64: =B21+D63 -> 2642.0194
A65: Beginner all-in with charge | B65: =C21+B63 -> 2838.314 | C65: =C21+C63 -> 2809.1962 | D65: =C21+D63 -> 2792.2109
A66: Approach 3 — per-head charge only (no free places)
A67: Per-head charge to participants | B67: =B56/B53 -> 184.10536 | C67: =B56/C53 -> 135.65658 | D67: =B56/D53 -> 107.39479
A68: Certified all-in with charge | B68: =B21+B67 -> 2761.5804 | C68: =B21+C67 -> 2713.1316 | D68: =B21+D67 -> 2684.8698
A69: Beginner all-in with charge | B69: =C21+B67 -> 2911.7719 | C69: =C21+C67 -> 2863.3231 | D69: =C21+D67 -> 2835.0613
A70: Second free place at 22+ guests: value per paying head if rebated | B70: 0 | C70: 0 | D70: =MAX(D54-1,0)*D55/D53 -> 42.850437
A71: Transfer rate at 21–30 people is lower (EUR 33 / 17): saving per person | B71: 0 | C71: 0 | D71: =2*(Inputs!$B$71-33)*Inputs!$B$6 -> 18.344
A74: D. Sensitivity (Royal Tent scenario, per person, before organiser charge)
A75: Airfare | B75: Low | C75: Midpoint | D75: High
A76: Fare used | B76: =Inputs!$B$53 -> 700 | C76: =AVERAGE(Inputs!$B$53,Inputs!$B$54) -> 1000 | D76: =Inputs!$B$54 -> 1300
A77: Certified total | B77: =B21-B7+B76 -> 2277.475 | C77: =B21-B7+C76 -> 2577.475 | D77: =B21-B7+D76 -> 2877.475
A78: Beginner total | B78: =C21-B7+B76 -> 2427.6665 | C78: =C21-B7+C76 -> 2727.6665 | D78: =C21-B7+D76 -> 3027.6665
A79: Advanced total | B79: =D21-B7+B76 -> 2662.699 | C79: =D21-B7+C76 -> 2962.699 | D79: =D21-B7+D76 -> 3262.699
A80: Fly to Marsa Alam instead (certified) | B80: =B21-B7+Inputs!$B$55-B8+2*Inputs!$B$69*Inputs!$B$6 -> 2833.908
A82: USD per EUR | B82: Euro 10% weaker | C82: Rate used | D82: Euro 10% stronger
A83: Rate | B83: =Inputs!$B$6*0.9 -> 1.03185 | C83: =Inputs!$B$6 -> 1.1465 | D83: =Inputs!$B$6*1.1 -> 1.26115
A84: Certified total at that rate | B84: =(B7+B18+B19+B20)+(B21-(B7+B18+B19+B20))*B83/Inputs!$B$6 -> 2445.6275 | C84: =(B7+B18+B19+B20)+(B21-(B7+B18+B19+B20))*C83/Inputs!$B$6 -> 2577.475 | D84: =(B7+B18+B19+B20)+(B21-(B7+B18+B19+B20))*D83/Inputs!$B$6 -> 2709.3225
A85: Beginner total at that rate | B85: =(C7+C18+C19+C20)+(C21-(C7+C18+C19+C20))*B83/Inputs!$B$6 -> 2580.7998 | C85: =(C7+C18+C19+C20)+(C21-(C7+C18+C19+C20))*C83/Inputs!$B$6 -> 2727.6665 | D85: =(C7+C18+C19+C20)+(C21-(C7+C18+C19+C20))*D83/Inputs!$B$6 -> 2874.5332
A88: E. Break-even group size (Royal Tent scenario)
A89: Certified: uncovered organiser cost after one free place | B89: =B56-B55 -> 1549.0645
A90: Certified: headroom under ceiling per person | B90: =Inputs!$B$17-B21 -> 122.525
A91: Certified: break-even group size incl. George | B91: =IF(B90>0,ROUNDUP(B89/B90,0)+1,"not viable at this price") -> 14
A92: Beginner: headroom under ceiling per person | B92: =Inputs!$B$17-C21 -> -27.6665
A93: Beginner: break-even group size incl. George | B93: =IF(B92>0,ROUNDUP(B89/B92,0)+1,"not viable at this price") -> not viable at this price
A94: RSDS first free place needs 11 guests, so 11 is the practical minimum for a free organiser place.
A97: F. Deposit schedule (draft, matched to advertised RSDS and Lufthansa group terms; QUOTE NEEDED)
A98: Milestone | B98: Date | C98: Amount per person | D98: Basis
A99: Participant deposit to club | B99: Fri 16 Oct 2026 | C99: 700 | D99: Covers RSDS deposit (up to 50% low season) and airline group deposit
A100: RSDS deposit (up to 50% of land package; 100% if 1–10 Jan is treated as a feast period) | B100: Fri 23 Oct 2026 | C100: =0.5*(B9+B8+B12) -> 514.20525 | D100: 50% of room, transfers, diving
A101: Lufthansa Group desk: pay within 7 days of confirmation; names 14 days before departure | B101: Contract + 7 days; names by Sat 19 Dec 2026 | C101: per contract | D101: LH group terms (snippet)
A102: Balance to club | B102: Fri 20 Nov 2026 | C102: =B21-700 -> 1877.475 | D102: Certified all-in less deposit
A103: RSDS balance (cancellation 20% if >30 days out) | B103: Wed 2 Dec 2026 | D103: RSDS ladder: >30 d 20%, 15–29 d 30%, 7–14 d 50%, <=6 d 80%
A104: Emperor Divers alternative: 20% non-refundable group deposit; 100% inside 30 days | D104: Emperor terms PDF (snippet)

Sheet Thanksgiving
A1: Thanksgiving — Puerto Rico (La Parguera) and Tiger Beach (Grand Bahama), 10 certified divers
A3: All figures per person, USD, 2 sharing, own dive gear. Car cost per head depends on group size (people per car on Inputs). Tiger Beach dives are BAITED shark dives; sales are final with a one-year weather credit.
A5: Group size incl. George | B5: 8 | C5: 10 | D5: 12
A7: A. Puerto Rico, Wed 25 – Sun 29 Nov (4 nights, 3 dive days)
A8: Item | B8: 8 people | C8: 10 people | D8: 12 people
A9: Flight PHL–SJU return nonstop (band midpoint) | B9: =AVERAGE(Inputs!$B$81,Inputs!$B$82) -> 550 | C9: =AVERAGE(Inputs!$B$81,Inputs!$B$82) -> 550 | D9: =AVERAGE(Inputs!$B$81,Inputs!$B$82) -> 550
A10: Car hire, fuel and tolls (shared) | B10: =(ROUNDUP(B5/Inputs!$B$94,0)*(Inputs!$B$83*Inputs!$B$93+Inputs!$B$95))/B5 -> 85 | C10: =(ROUNDUP(C5/Inputs!$B$94,0)*(Inputs!$B$83*Inputs!$B$93+Inputs!$B$95))/C5 -> 102 | D10: =(ROUNDUP(D5/Inputs!$B$94,0)*(Inputs!$B$83*Inputs!$B$93+Inputs!$B$95))/D5 -> 85
A11: Lodging, 2 sharing | B11: =Inputs!$B$83*Inputs!$B$85 -> 300 | C11: =Inputs!$B$83*Inputs!$B$85 -> 300 | D11: =Inputs!$B$83*Inputs!$B$85 -> 300
A12: Wall dives (two-tank days less Desecheo days) | B12: =(Inputs!$B$89-Inputs!$B$91)*Inputs!$B$87 -> 274 | C12: =(Inputs!$B$89-Inputs!$B$91)*Inputs!$B$87 -> 274 | D12: =(Inputs!$B$89-Inputs!$B$91)*Inputs!$B$87 -> 274
A13: Desecheo day incl. park fee (weather permitting) | B13: =Inputs!$B$91*Inputs!$B$88 -> 140 | C13: =Inputs!$B$91*Inputs!$B$88 -> 140 | D13: =Inputs!$B$91*Inputs!$B$88 -> 140
A14: Bio bay evening | B14: =Inputs!$B$92 -> 45 | C14: =Inputs!$B$92 -> 45 | D14: =Inputs!$B$92 -> 45
A15: Meals and incidentals | B15: =Inputs!$B$83*Inputs!$B$21 -> 140 | C15: =Inputs!$B$83*Inputs!$B$21 -> 140 | D15: =Inputs!$B$83*Inputs!$B$21 -> 140
A16: Tips and local extras | B16: =Inputs!$B$22 -> 50 | C16: =Inputs!$B$22 -> 50 | D16: =Inputs!$B$22 -> 50
A17: Dive-accident insurance | B17: =Inputs!$B$20 -> 119 | C17: =Inputs!$B$20 -> 119 | D17: =Inputs!$B$20 -> 119
A18: Total per person | B18: =SUM(B9:B17) -> 1703 | C18: =SUM(C9:C17) -> 1720 | D18: =SUM(D9:D17) -> 1703
A19: of which core: flights, transfers, lodging, diving, fees (excl. meals, tips, insurance) | B19: =B18-SUM(B15:B17) -> 1394 | C19: =C18-SUM(C15:C17) -> 1411 | D19: =D18-SUM(D15:D17) -> 1394
A20: Budget ceiling | B20: =Inputs!$B$14 -> 1500 | C20: =Inputs!$B$14 -> 1500 | D20: =Inputs!$B$14 -> 1500
A21: Headroom (negative = over ceiling) | B21: =B20-B18 -> -203 | C21: =C20-C18 -> -220 | D21: =D20-D18 -> -203
A24: B. Puerto Rico, Thu 19 – Tue 24 Nov (5 nights, 4 dive days; four class days missed; Colombia trek clash)
A25: Item | B25: 8 people | C25: 10 people | D25: 12 people
A26: Flight PHL–SJU return nonstop (band midpoint) | B26: =AVERAGE(Inputs!$B$81,Inputs!$B$82) -> 550 | C26: =AVERAGE(Inputs!$B$81,Inputs!$B$82) -> 550 | D26: =AVERAGE(Inputs!$B$81,Inputs!$B$82) -> 550
A27: Car hire, fuel and tolls (shared) | B27: =(ROUNDUP(B5/Inputs!$B$94,0)*(Inputs!$B$84*Inputs!$B$93+Inputs!$B$95))/B5 -> 102.5 | C27: =(ROUNDUP(C5/Inputs!$B$94,0)*(Inputs!$B$84*Inputs!$B$93+Inputs!$B$95))/C5 -> 123 | D27: =(ROUNDUP(D5/Inputs!$B$94,0)*(Inputs!$B$84*Inputs!$B$93+Inputs!$B$95))/D5 -> 102.5
A28: Lodging, 2 sharing | B28: =Inputs!$B$84*Inputs!$B$85 -> 375 | C28: =Inputs!$B$84*Inputs!$B$85 -> 375 | D28: =Inputs!$B$84*Inputs!$B$85 -> 375
A29: Wall dives (two-tank days less Desecheo days) | B29: =(Inputs!$B$90-Inputs!$B$91)*Inputs!$B$87 -> 411 | C29: =(Inputs!$B$90-Inputs!$B$91)*Inputs!$B$87 -> 411 | D29: =(Inputs!$B$90-Inputs!$B$91)*Inputs!$B$87 -> 411
A30: Desecheo day incl. park fee (weather permitting) | B30: =Inputs!$B$91*Inputs!$B$88 -> 140 | C30: =Inputs!$B$91*Inputs!$B$88 -> 140 | D30: =Inputs!$B$91*Inputs!$B$88 -> 140
A31: Bio bay evening | B31: =Inputs!$B$92 -> 45 | C31: =Inputs!$B$92 -> 45 | D31: =Inputs!$B$92 -> 45
A32: Meals and incidentals | B32: =Inputs!$B$84*Inputs!$B$21 -> 175 | C32: =Inputs!$B$84*Inputs!$B$21 -> 175 | D32: =Inputs!$B$84*Inputs!$B$21 -> 175
A33: Tips and local extras | B33: =Inputs!$B$22 -> 50 | C33: =Inputs!$B$22 -> 50 | D33: =Inputs!$B$22 -> 50
A34: Dive-accident insurance | B34: =Inputs!$B$20 -> 119 | C34: =Inputs!$B$20 -> 119 | D34: =Inputs!$B$20 -> 119
A35: Total per person | B35: =SUM(B26:B34) -> 1967.5 | C35: =SUM(C26:C34) -> 1988 | D35: =SUM(D26:D34) -> 1967.5
A36: of which core: flights, transfers, lodging, diving, fees (excl. meals, tips, insurance) | B36: =B35-SUM(B32:B34) -> 1623.5 | C36: =C35-SUM(C32:C34) -> 1644 | D36: =D35-SUM(D32:D34) -> 1623.5
A37: Budget ceiling | B37: =Inputs!$B$14 -> 1500 | C37: =Inputs!$B$14 -> 1500 | D37: =Inputs!$B$14 -> 1500
A38: Headroom (negative = over ceiling) | B38: =B37-B35 -> -467.5 | C38: =C37-C35 -> -488 | D38: =D37-D35 -> -467.5
A41: C. Tiger Beach variant, Wed 25 – Sun 29 Nov (4 nights, 2 shark days + weather buffer)
A42: Item | B42: 8 people | C42: 10 people | D42: 12 people
A43: Flights PHL–FLL and FLL–FPO return | B43: =Inputs!$B$100+Inputs!$B$101 -> 600 | C43: =Inputs!$B$100+Inputs!$B$101 -> 600 | D43: =Inputs!$B$100+Inputs!$B$101 -> 600
A44: Airport – West End transfers | B44: =Inputs!$B$105 -> 50 | C44: =Inputs!$B$105 -> 50 | D44: =Inputs!$B$105 -> 50
A45: Lodging Old Bahama Bay, 2 sharing | B45: =Inputs!$B$83*Inputs!$B$103 -> 500 | C45: =Inputs!$B$83*Inputs!$B$103 -> 500 | D45: =Inputs!$B$83*Inputs!$B$103 -> 500
A46: Shark days (BAITED), incl. VAT | B46: =Inputs!$B$98*Inputs!$B$96*(1+Inputs!$B$97) -> 877.8 | C46: =Inputs!$B$98*Inputs!$B$96*(1+Inputs!$B$97) -> 877.8 | D46: =Inputs!$B$98*Inputs!$B$96*(1+Inputs!$B$97) -> 877.8
A47: Wetsuit rental if needed | B47: =Inputs!$B$98*Inputs!$B$106 -> 30 | C47: =Inputs!$B$98*Inputs!$B$106 -> 30 | D47: =Inputs!$B$98*Inputs!$B$106 -> 30
A48: Meals and incidentals | B48: =Inputs!$B$83*Inputs!$B$21 -> 140 | C48: =Inputs!$B$83*Inputs!$B$21 -> 140 | D48: =Inputs!$B$83*Inputs!$B$21 -> 140
A49: Tips and local extras | B49: =Inputs!$B$22 -> 50 | C49: =Inputs!$B$22 -> 50 | D49: =Inputs!$B$22 -> 50
A50: Dive-accident insurance | B50: =Inputs!$B$20 -> 119 | C50: =Inputs!$B$20 -> 119 | D50: =Inputs!$B$20 -> 119
A51: Total per person | B51: =SUM(B43:B50) -> 2366.8 | C51: =SUM(C43:C50) -> 2366.8 | D51: =SUM(D43:D50) -> 2366.8
A52: of which core: flights, transfers, lodging, diving, fees (excl. meals, tips, insurance) | B52: =B51-SUM(B48:B50) -> 2057.8 | C52: =C51-SUM(C48:C50) -> 2057.8 | D52: =D51-SUM(D48:D50) -> 2057.8
A53: Budget ceiling | B53: =Inputs!$B$14 -> 1500 | C53: =Inputs!$B$14 -> 1500 | D53: =Inputs!$B$14 -> 1500
A54: Headroom (negative = over ceiling) | B54: =B53-B51 -> -866.8 | C54: =C53-C51 -> -866.8 | D54: =D53-D51 -> -866.8
A55: Extra cost vs Puerto Rico, same dates | B55: =B51-B18 -> 663.8 | C55: =C51-C18 -> 646.8 | D55: =D51-D18 -> 663.8
A56: Ferry instead of FLL–FPO flight: saving per person | B56: =Inputs!$B$101-Inputs!$B$102 -> 60 | C56: =Inputs!$B$101-Inputs!$B$102 -> 60 | D56: =Inputs!$B$101-Inputs!$B$102 -> 60
A59: D. Tiger Beach variant, Thu 19 – Tue 24 Nov (5 nights, 3 shark days)
A60: Item | B60: 8 people | C60: 10 people | D60: 12 people
A61: Flights PHL–FLL and FLL–FPO return | B61: =Inputs!$B$100+Inputs!$B$101 -> 600 | C61: =Inputs!$B$100+Inputs!$B$101 -> 600 | D61: =Inputs!$B$100+Inputs!$B$101 -> 600
A62: Airport – West End transfers | B62: =Inputs!$B$105 -> 50 | C62: =Inputs!$B$105 -> 50 | D62: =Inputs!$B$105 -> 50
A63: Lodging Old Bahama Bay, 2 sharing | B63: =Inputs!$B$84*Inputs!$B$103 -> 625 | C63: =Inputs!$B$84*Inputs!$B$103 -> 625 | D63: =Inputs!$B$84*Inputs!$B$103 -> 625
A64: Shark days (BAITED), incl. VAT | B64: =Inputs!$B$99*Inputs!$B$96*(1+Inputs!$B$97) -> 1316.7 | C64: =Inputs!$B$99*Inputs!$B$96*(1+Inputs!$B$97) -> 1316.7 | D64: =Inputs!$B$99*Inputs!$B$96*(1+Inputs!$B$97) -> 1316.7
A65: Wetsuit rental if needed | B65: =Inputs!$B$99*Inputs!$B$106 -> 45 | C65: =Inputs!$B$99*Inputs!$B$106 -> 45 | D65: =Inputs!$B$99*Inputs!$B$106 -> 45
A66: Meals and incidentals | B66: =Inputs!$B$84*Inputs!$B$21 -> 175 | C66: =Inputs!$B$84*Inputs!$B$21 -> 175 | D66: =Inputs!$B$84*Inputs!$B$21 -> 175
A67: Tips and local extras | B67: =Inputs!$B$22 -> 50 | C67: =Inputs!$B$22 -> 50 | D67: =Inputs!$B$22 -> 50
A68: Dive-accident insurance | B68: =Inputs!$B$20 -> 119 | C68: =Inputs!$B$20 -> 119 | D68: =Inputs!$B$20 -> 119
A69: Total per person | B69: =SUM(B61:B68) -> 2980.7 | C69: =SUM(C61:C68) -> 2980.7 | D69: =SUM(D61:D68) -> 2980.7
A70: of which core: flights, transfers, lodging, diving, fees (excl. meals, tips, insurance) | B70: =B69-SUM(B66:B68) -> 2636.7 | C70: =C69-SUM(C66:C68) -> 2636.7 | D70: =D69-SUM(D66:D68) -> 2636.7
A71: Budget ceiling | B71: =Inputs!$B$14 -> 1500 | C71: =Inputs!$B$14 -> 1500 | D71: =Inputs!$B$14 -> 1500
A72: Headroom (negative = over ceiling) | B72: =B71-B69 -> -1480.7 | C72: =C71-C69 -> -1480.7 | D72: =D71-D69 -> -1480.7
A73: Extra cost vs Puerto Rico, same dates | B73: =B69-B35 -> 1013.2 | C73: =C69-C35 -> 992.7 | D73: =D69-D35 -> 1013.2
A76: E. Organiser place (Puerto Rico, 25–29 Nov)
A77: No Puerto Rico operator advertises a free leader place; at 8–12 divers the diving-only value is small. Approaches shown for disclosure.
A78: Paying participants | B78: =B5-1 -> 7 | C78: =C5-1 -> 9 | D78: =D5-1 -> 11
A79: Value of a free diving place (Wall + Desecheo days) | B79: =B12+B13 -> 414 | C79: =C12+C13 -> 414 | D79: =D12+D13 -> 414
A80: George's all-in cost | B80: =B18 -> 1703 | C80: =C18 -> 1720 | D80: =D18 -> 1703
A81: Approach 1 — free diving place only (if quoted): George pays | B81: =B80-B79 -> 1289 | C81: =C80-C79 -> 1306 | D81: =D80-D79 -> 1289
A82: Approach 2 — free place plus per-head charge: charge per person | B82: =(B80-B79)/B78 -> 184.14286 | C82: =(C80-C79)/C78 -> 145.11111 | D82: =(D80-D79)/D78 -> 117.18182
A83: Approach 3 — per-head charge only: charge per person | B83: =B80/B78 -> 243.28571 | C83: =C80/C78 -> 191.11111 | D83: =D80/D78 -> 154.81818
A84: All-in per person with Approach 3 | B84: =B18+B83 -> 1946.2857 | C84: =C18+C83 -> 1911.1111 | D84: =D18+D83 -> 1857.8182
A87: F. Sensitivity (Puerto Rico 25–29 Nov, 10 people)
A88: Airfare | B88: Low | C88: Midpoint | D88: High
A89: Fare used | B89: =Inputs!$B$81 -> 400 | C89: =AVERAGE(Inputs!$B$81,Inputs!$B$82) -> 550 | D89: =Inputs!$B$82 -> 700
A90: Total per person | B90: =C18-C9+B89 -> 1570 | C90: =C18-C9+C89 -> 1720 | D90: =C18-C9+D89 -> 1870
A91: Desecheo cancelled, replaced by a third Wall day (10 people) | B91: =C18-C13+Inputs!$B$87 -> 1717
A92: 3 sharing instead of 2 (10 people) | B92: =C18-Inputs!$B$83*(Inputs!$B$85-Inputs!$B$86) -> 1620
A95: G. Break-even and minimum viable numbers
A96: Puerto Rico: headroom under ceiling at 10 people | B96: =Inputs!$B$14-C18 -> -220
A97: Puerto Rico: break-even group size incl. George (Approach 3) | B97: =IF(B96>0,ROUNDUP(C80/B96,0)+1,"not viable at this price") -> not viable at this price
A98: Puerto Rico boat: Paradise Scuba capacity for 10–12 on one departure QUOTE NEEDED; two departures otherwise
A99: Tiger Beach: over the ceiling at every group size; minimum viable is whatever the boat charter needs (QUOTE NEEDED)
A102: H. Deposit schedule (draft; all terms QUOTE NEEDED)
A103: Milestone | B103: Date | C103: Amount per person | D103: Basis
A104: Participant deposit to club | B104: Fri 2 Oct 2026 | C104: 400 | D104: Covers hotel and dive deposits; Thanksgiving fares move fast
A105: Flights booked individually or via AA group desk (10+) | B105: by Fri 9 Oct 2026 | C105: =AVERAGE(Inputs!$B$81,Inputs!$B$82) -> 550 | D105: Fare midpoint
A106: Hotel block deposit (one night per room, typical) | B106: Fri 9 Oct 2026 | C106: =Inputs!$B$85 -> 75 | D106: One night, 2 sharing
A107: Dive operator deposit (Paradise Scuba terms QUOTE NEEDED) | B107: Fri 16 Oct 2026 | C107: =0.25*(C12+C13) -> 103.5 | D107: 25% assumed
A108: Balance to club | B108: Fri 6 Nov 2026 | C108: =C18-400 -> 1320 | D108: 10-person all-in less deposit
A109: Tiger Beach: full payment at booking, sales final, one-year weather credit | B109: at booking | C109: =Inputs!$B$98*Inputs!$B$96*(1+Inputs!$B$97) -> 877.8 | D109: Neal Watson terms (snippet)
