Workbook

Sheet Inputs
A1: Egypt group budget — inputs (blue cells are editable; EUR unless stated)
A2: item | B2: value | C2: unit | D2: flag / source
A3: Pricing basis
A4: USD per EUR | B4: 1.1465 | C4: USD/EUR | D4: ADVERTISED mid-market 21 Sep 2026 (sources.csv)
A5: Pricing headcount: people including George at which the fee is set | B5: 20 | C5: people | D5: policy: conservative
A6: Minimum headcount the contingency must cover | B6: 12 | C6: people | D6: policy (11 paying = first free place)
A7: Share of participants who are Open Water students | B7: 0.5 | C7: share | D7: brief
A8: Contingency inside the fee (refunded pro rata if unused) | B8: 0.06 | C8: share | D8: policy
A9: Red Sea Diving Safari, Marsa Shagra (QUOTED 24 Sep 2026, Riad Tarek, low season, per person)
A10: Royal Tent, double, full board, per person per night | B10: 78 | C10: EUR/night | D10: QUOTED 26 Sep (390 for five nights; Deluxe Chalet 113/night = 565)
A11: Nights, Sun 3 – Fri 8 Jan | B11: 5 | C11: nights | D11: programme
A12: House reef diving, four one-day unlimited passes Mon–Thu (certified), EUR 77 a day | B12: 308 | C12: EUR | D12: QUOTED 26 Sep (no four-day package; cheaper than the five-day 347)
A13: One-day unlimited house-reef pass (the new divers' Thursday after certification) | B13: 77 | C13: EUR | D13: QUOTED 26 Sep
A14: Open Water course incl. equipment | B14: 358 | C14: EUR | D14: QUOTED
A15: PADI e-code / certification per beginner | B15: 94 | C15: EUR | D15: QUOTED
A16: Advanced Open Water incl. equipment (add-on) | B16: 286 | C16: EUR | D16: QUOTED (242 with own gear)
A17: Dolphin House day boat (certified, Wed) incl. park fee | B17: 67 | C17: EUR | D17: QUOTED 48 + 19
A18: Elphinstone speedboat dive (add-on, AOW) | B18: 36 | C18: EUR/dive | D18: QUOTED
A19: Environmental fee 10 + hyperbaric fee 7, once per person | B19: 17 | C19: EUR | D19: QUOTED
A20: Full equipment rental incl. computer per day, certified divers (course prices include gear) | B20: 39 | C20: EUR/day | D20: QUOTED 26 Sep (33 without computer; club rule: computers inside the fee)
A21: Rental days, certified (Mon–Thu) | B21: 4 | C21: days | D21: programme
... A24: RSDS deposit at booking (non-refundable) | B24: 0.2 | C24: share | D24: QUOTED 26 Sep; balance on site, 5% off for cash, card +3%
A25: Leader costs carried by the group (George's lodging and diving come from the first free place)
A26: George's flight allowance | B26: 1000 | C26: USD | D26: policy; PHL–HRG band 700–1,300 (sources.csv)
A27: Odd-headcount room risk (one person alone at the group's cost, single supplement unknown) | B27: =Inputs!$B$10*Inputs!$B$11*0.5 -> 195 | C27: EUR | D27: ASSUMED half a place
A28: George's gear rental, 4 days | B28: =Inputs!$B$20*4 -> 156 | C28: EUR | D28: formula
A29: Own spending guidance, not in the fee (no flights)
A30: Airport transfers both ways, Hurghada, 10–20 pax rate | B30: 82 | C30: EUR | D30: QUOTED 41 each way (33 at 21–30 pax; Marsa Alam 22 / 17)
A31: Dive-accident cover, required, bought by each person | B31: 84 | C31: USD | D31: ADVERTISED: DAN membership 40 + Master 44 (short-term plan about 50 if sold locally)
A32: Egypt visa on arrival | B32: 30 | C32: USD | D32: DOCUMENTED (secondary): USD 30 since 1 Mar 2026
A33: Visa on arrival plus meet-and-assist at the airport (optional, minimum four) | B33: 45 | C33: EUR | D33: QUOTED 26 Sep
A34: Drinks, snacks, tips per day (full board covers meals) | B34: 20 | C34: USD/day | D34: INFERRED
A35: Days at the village | B35: 5 | C35: days
A36: Tips for guides and staff | B36: 50 | C36: USD | D36: INFERRED

Sheet Fee
A1: Trip fee per person, set at the pricing headcount (EUR lines, USD fee; 2 sharing, full board)
B2: Open Water student | C2: Certified diver
A3: Diving with RSDS (course + e-code + Thursday pass, or four day passes Mon–Thu) | B3: =Inputs!$B$14+Inputs!$B$15+Inputs!$B$13 -> 529 | C3: =Inputs!$B$12 -> 308
A4: Dolphin House day boat incl. park fee (certified, Wed) | B4: 0 | C4: =Inputs!$B$17 -> 67
A5: Gear rental | B5: =Inputs!$B$20*Inputs!$B$22 -> 39 | C5: =Inputs!$B$20*Inputs!$B$21 -> 156
A6: Environmental and hyperbaric fees | B6: =Inputs!$B$19 -> 17 | C6: =Inputs!$B$19 -> 17
A7: Royal Tent, 5 nights full board, 2 sharing | B7: =Inputs!$B$10*Inputs!$B$11 -> 390 | C7: =Inputs!$B$10*Inputs!$B$11 -> 390
A8: Leader's costs shared (George's flight allowance, gear, odd-room risk) | B8: =(Inputs!$B$26/Inputs!$B$4+Inputs!$B$27+Inputs!$B$28)/(Inputs!$B$5-1) -> 64.379989 | C8: =(Inputs!$B$26/Inputs!$B$4+Inputs!$B$27+Inputs!$B$28)/(Inputs!$B$5-1) -> 64.379989
A9: Subtotal, EUR | B9: =SUM(B3:B8) -> 1039.38 | C9: =SUM(C3:C8) -> 1002.38
A10: Contingency, EUR | B10: =ROUND(B9*Inputs!$B$8,0) -> 62 | C10: =ROUND(C9*Inputs!$B$8,0) -> 60
A11: Fee in USD before rounding | B11: =(B9+B10)*Inputs!$B$4 -> 1262.7322 | C11: =(C9+C10)*Inputs!$B$4 -> 1218.0187
A12: TRIP FEE, USD (rounded up to the nearest 50, as posted) | B12: =CEILING(B11,50) -> 1300 | C12: =CEILING(C11,50) -> 1250
A14: Optional add-ons at sign-up, charged at cost (USD)
A15: Advanced Open Water incl. equipment | B15: n/a | C15: =Inputs!$B$16*Inputs!$B$4 -> 327.899
A16: Elphinstone speedboat dive, each | B16: n/a | C16: =Inputs!$B$18*Inputs!$B$4 -> 41.274
A17: Abu Dabbab afternoon (48) | B17: =48*Inputs!$B$4 -> 55.032 | C17: =48*Inputs!$B$4 -> 55.032
A19: GUIDANCE BUDGET WITHOUT FLIGHTS (USD)
A20: Trip fee | B20: =B12 -> 1300 | C20: =C12 -> 1250
A21: Own spending: transfers, dive cover, visa, meet-and-assist, drinks, tips | B21: =(Inputs!$B$30+Inputs!$B$33)*Inputs!$B$4+Inputs!$B$31+Inputs!$B$32+Inputs!$B$34*Inputs!$B$35+Inputs!$B$36 -> 409.6055 | C21: =(Inputs!$B$30+Inputs!$B$33)*Inputs!$B$4+Inputs!$B$31+Inputs!$B$32+Inputs!$B$34*Inputs!$B$35+Inputs!$B$36 -> 409.6055
A22: Guidance budget | B22: =B20+B21 -> 1709.6055 | C22: =C20+C21 -> 1659.6055
A23: Guidance budget, certified taking AOW and one Elphinstone dive | B23: n/a | C23: =C22+C15+C16 -> 2028.7785
A25: The fee covers everything diving-related (course, e-code, package, gear, fees) and five nights full board at Marsa Shagra; flights, transfers, dive-accident cover, visa, drinks and tips are each person's own. Set at the pricing headcount; a bigger group makes a surplus that is refunded pro rata or held; the contingency covers a shortfall down to the minimum. George's place: lodging and diving from RSDS's first free place, flight allowance carried by the group, all disclosed on the sign-up page.

Sheet Group
A1: Group budget at four sizes, EUR unless stated (half students; George leads and does not pay)
B2: 12 people (minimum) | C2: 20 people (pricing basis) | D2: 25 people | E2: 30 people
A3: People including George | B3: 12 | C3: 20 | D3: 25 | E3: 30
A4: Paying participants | B4: =B3-1 -> 11 | C4: =C3-1 -> 19 | D4: =D3-1 -> 24 | E4: =E3-1 -> 29
A5: Open Water students | B5: =ROUND(B4*Inputs!$B$7,0) -> 6 | C5: =ROUND(C4*Inputs!$B$7,0) -> 10 | D5: =ROUND(D4*Inputs!$B$7,0) -> 12 | E5: =ROUND(E4*Inputs!$B$7,0) -> 15
A6: Paying certified divers | B6: =B4-B5 -> 5 | C6: =C4-C5 -> 9 | D6: =D4-D5 -> 12 | E6: =E4-E5 -> 14
A7: Free places earned (11th, 21st, 30th paying guest) | B7: =(B4>=11)+(B4>=21)+(B4>=30) -> 1 | C7: =(C4>=11)+(C4>=21)+(C4>=30) -> 1 | D7: =(D4>=11)+(D4>=21)+(D4>=30) -> 2 | E7: =(E4>=11)+(E4>=21)+(E4>=30) -> 2
A8: Revenue (USD fees converted to EUR)
A9: Trip fees collected | B9: =(B5*Fee!$B$12+B6*Fee!$C$12)/Inputs!$B$4 -> 12254.688 | C9: =(C5*Fee!$B$12+C6*Fee!$C$12)/Inputs!$B$4 -> 21151.33 | D9: =(D5*Fee!$B$12+D6*Fee!$C$12)/Inputs!$B$4 -> 26689.926 | E9: =(E5*Fee!$B$12+E6*Fee!$C$12)/Inputs!$B$4 -> 32272.133
A10: Costs
A11: Lodging, paying guests, full board | B11: =B4*Inputs!$B$10*Inputs!$B$11 -> 4290 | C11: =C4*Inputs!$B$10*Inputs!$B$11 -> 7410 | D11: =D4*Inputs!$B$10*Inputs!$B$11 -> 9360 | E11: =E4*Inputs!$B$10*Inputs!$B$11 -> 11310
A12: Open Water courses, e-codes and Thursday day | B12: =B5*(Inputs!$B$14+Inputs!$B$15+Inputs!$B$13) -> 3174 | C12: =C5*(Inputs!$B$14+Inputs!$B$15+Inputs!$B$13) -> 5290 | D12: =D5*(Inputs!$B$14+Inputs!$B$15+Inputs!$B$13) -> 6348 | E12: =E5*(Inputs!$B$14+Inputs!$B$15+Inputs!$B$13) -> 7935
A13: House reef packages and Dolphin House, paying certified | B13: =B6*(Inputs!$B$12+Inputs!$B$17) -> 1875 | C13: =C6*(Inputs!$B$12+Inputs!$B$17) -> 3375 | D13: =D6*(Inputs!$B$12+Inputs!$B$17) -> 4500 | E13: =E6*(Inputs!$B$12+Inputs!$B$17) -> 5250
A14: George's lodging and package (free if a free place is earned) | B14: =IF(B7>=1,0,Inputs!$B$10*Inputs!$B$11+Inputs!$B$12) -> 0 | C14: =IF(C7>=1,0,Inputs!$B$10*Inputs!$B$11+Inputs!$B$12) -> 0 | D14: =IF(D7>=1,0,Inputs!$B$10*Inputs!$B$11+Inputs!$B$12) -> 0 | E14: =IF(E7>=1,0,Inputs!$B$10*Inputs!$B$11+Inputs!$B$12) -> 0
A15: Spare free places credited against the invoice (lodging + package) | B15: =-MAX(B7-1,0)*(Inputs!$B$10*Inputs!$B$11+Inputs!$B$12) -> 0 | C15: =-MAX(C7-1,0)*(Inputs!$B$10*Inputs!$B$11+Inputs!$B$12) -> 0 | D15: =-MAX(D7-1,0)*(Inputs!$B$10*Inputs!$B$11+Inputs!$B$12) -> -698 | E15: =-MAX(E7-1,0)*(Inputs!$B$10*Inputs!$B$11+Inputs!$B$12) -> -698
A16: Environmental and hyperbaric fees, everyone | B16: =B3*Inputs!$B$19 -> 204 | C16: =C3*Inputs!$B$19 -> 340 | D16: =D3*Inputs!$B$19 -> 425 | E16: =E3*Inputs!$B$19 -> 510
A17: RSDS invoice | B17: =B11+B12+B13+B14+B15+B16 -> 9543 | C17: =C11+C12+C13+C14+C15+C16 -> 16415 | D17: =D11+D12+D13+D14+D15+D16 -> 19935 | E17: =E11+E12+E13+E14+E15+E16 -> 24307
A18: Gear rental (certified incl. George 4 days; students 1 day) | B18: =(B6+1)*Inputs!$B$20*Inputs!$B$21+B5*Inputs!$B$20*Inputs!$B$22 -> 1170 | C18: =(C6+1)*Inputs!$B$20*Inputs!$B$21+C5*Inputs!$B$20*Inputs!$B$22 -> 1950 | D18: =(D6+1)*Inputs!$B$20*Inputs!$B$21+D5*Inputs!$B$20*Inputs!$B$22 -> 2496 | E18: =(E6+1)*Inputs!$B$20*Inputs!$B$21+E5*Inputs!$B$20*Inputs!$B$22 -> 2925
A19: Odd-headcount room risk | B19: =IF(MOD(B3,2)=1,Inputs!$B$27,0) -> 0 | C19: =IF(MOD(C3,2)=1,Inputs!$B$27,0) -> 0 | D19: =IF(MOD(D3,2)=1,Inputs!$B$27,0) -> 195 | E19: =IF(MOD(E3,2)=1,Inputs!$B$27,0) -> 0
A20: George's flight allowance (EUR) | B20: =Inputs!$B$26/Inputs!$B$4 -> 872.2198 | C20: =Inputs!$B$26/Inputs!$B$4 -> 872.2198 | D20: =Inputs!$B$26/Inputs!$B$4 -> 872.2198 | E20: =Inputs!$B$26/Inputs!$B$4 -> 872.2198
A21: TOTAL COSTS | B21: =B17+B18+B19+B20 -> 11585.22 | C21: =C17+C18+C19+C20 -> 19237.22 | D21: =D17+D18+D19+D20 -> 23498.22 | E21: =E17+E18+E19+E20 -> 28104.22
A22: Result
A23: Surplus, EUR (contingency and over-recovery; refunded pro rata or held) | B23: =B9-B21 -> 669.46838 | C23: =C9-C21 -> 1914.1103 | D23: =D9-D21 -> 3191.7061 | E23: =E9-E21 -> 4167.9128
A24: Surplus, USD | B24: =B23*Inputs!$B$4 -> 767.5455 | C24: =C23*Inputs!$B$4 -> 2194.5275 | D24: =D23*Inputs!$B$4 -> 3659.291 | E24: =E23*Inputs!$B$4 -> 4778.512
A25: Covered? (surplus must stay positive at the minimum headcount) | B25: =IF(B23>=0,"yes","NO") -> yes | C25: =IF(C23>=0,"yes","NO") -> yes | D25: =IF(D23>=0,"yes","NO") -> yes | E25: =IF(E23>=0,"yes","NO") -> yes
A26: George's pot, EUR: value of spare free places (no commission offered) | B26: =-B15 -> 0 | C26: =-C15 -> 0 | D26: =-D15 -> 698 | E26: =-E15 -> 698
A27: Deposits and cash (RSDS: 20% non-refundable at booking, balance on site)
A28: Participant deposits at sign-up (USD 400 each, in EUR) | B28: =B4*400/Inputs!$B$4 -> 3837.7671 | C28: =C4*400/Inputs!$B$4 -> 6628.8705 | D28: =D4*400/Inputs!$B$4 -> 8373.3101 | E28: =E4*400/Inputs!$B$4 -> 10117.75
A29: RSDS deposit (share of invoice) | B29: =B17*Inputs!$B$24 -> 1908.6 | C29: =C17*Inputs!$B$24 -> 3283 | D29: =D17*Inputs!$B$24 -> 3987 | E29: =E17*Inputs!$B$24 -> 4861.4
A30: Deposit cover (positive means deposits fund the outflow) | B30: =B28-B29 -> 1929.1671 | C30: =C28-C29 -> 3345.8705 | D30: =D28-D29 -> 4386.3101 | E30: =E28-E29 -> 5256.3497
A31: Notes: fees are posted in USD and converted at the workbook rate, so a weaker dollar eats the surplus first; the contingency and the 12-person floor are the cushion. A free place beyond George's own is credited to the club here; George can instead ask to keep it as his pot (a TDI course, parked). Paying the balance in cash on site earns a 5% discount on the RSDS invoice, not modelled.

Sheet Payments
A1: Payment schedule (RSDS terms quoted 26 Sep; dates provisional)
A2: date | B2: what | C2: who
A3: by Fri 9 Oct | B3: Sign-ups open on CampusGroups; deposit USD 400 per person holds a place | C3: participants
A4: Fri 16 Oct | B4: Sign-up deadline; headcount and course split to RSDS | C4: George
A5: by Fri 23 Oct | B5: RSDS deposit, 20% of the invoice, non-refundable, by bank transfer or card; e-codes issued to students | C5: club account
A6: Fri 13 Nov | B6: Participant balances due (fee less deposit, plus add-ons) | C6: participants
A7: Fri 8 Jan, on site | B7: RSDS balance paid on departure: cash in EUR earns 5% off, card in EGP costs 3% (George carries the club card or a bank draft; decide in December) | C7: George / club account
A8: Sun 3 Jan | B8: Arrival; transfers, visa and dive cover are each person's own | C8: George
A9: after the trip | B9: Unused contingency and any surplus refunded pro rata | C9: club account
A11: Refund ladder | B11: Mirrors RSDS: deposit non-refundable once paid to RSDS (23 Oct); cancellation more than 30 days out costs 20% of the place, 15–29 days 30%, 7–14 days 50%, 6 days or less 80%, no-show 100%; a resold place is refunded in full less the club's costs. | C11: policy
A12: Cancellation ladder (RSDS) | B12: >30 days 20% / 15–29 days 30% / 7–14 days 50% / <=6 days 80% / no-show 100%; low season 3–8 Jan, no supplements | C12: QUOTED 26 Sep
A13: Money handling | B13: All payments through CampusGroups or RSDS's own link, never personal Venmo or Zelle. The sign-up page states that the leader's place comes from the village's free-place rule and his flight allowance is carried by the group. | C13: policy
