Workbook

Sheet Inputs
A1: Thanksgiving (Puerto Rico) group budget — inputs (blue cells are editable)
A2: item | B2: value | C2: unit | D2: flag / source
A3: Pricing basis
A4: Pricing headcount including George | B4: 10 | C4: people | D4: policy: conservative (group is 8–12)
A5: Contingency inside the fee (refunded pro rata if unused) | B5: 0.06 | C5: share | D5: policy
A6: Paradise Scuba, La Parguera (QUOTED 22 Sep 2026, Kiko)
A7: Two-tank Wall dive, list price | B7: 145 | C7: USD | D7: QUOTED
A8: Group discount | B8: 0.15 | C8: share | D8: QUOTED
A9: Puerto Rico sales tax (IVU) | B9: 0.115 | C9: share | D9: QUOTED 24 Sep (Edwin, Paradise Scuba)
A10: Boat mornings (Thu, Fri, Sat; Sat out of the water by noon) | B10: 3 | C10: days | D10: programme
A11: Gear rental per day, everyone rents | B11: 25 | C11: USD/day | D11: QUOTED
A12: Night dive, single tank with lights, list price (optional add-on; group discount and tax apply) | B12: 140 | C12: USD | D12: QUOTED 24 Sep; gear rental 25 extra
A13: Third dive the same afternoon | B13: 0 | C13: USD | D13: NOT OFFERED (Paradise 24 Sep: air only, nitrogen loading); night dive instead
A14: Paradise Scuba deposit | B14: 0.5 | C14: share | D14: QUOTED; refundable to 30 days out
A15: Lodging (Parador Villa Parguera; QUOTE NEEDED, chased 24 Sep)
A16: Room per night, 2 sharing (Nautilus Hotel, tax included) | B16: 176.7 | C16: USD | D16: QUOTED 30 Sep (Nautilus by La Jamaca: 155 + tax; grab-and-go breakfast optional, price to confirm)
A17: Nights (Wed 25 – Sun 29 Nov) | B17: 4 | C17: nights
A18: Hotel deposit at booking (share) | B18: 0.25 | C18: share | D18: assumption
A19: Cars (in the group budget, George 23 Sep)
A20: Hire car per day, mid-size from SJU | B20: 70 | C20: USD/day | D20: INFERRED; QUOTE NEEDED
A21: Rental days | B21: 5 | C21: days | D21: Wed to Sun
A22: Fuel and tolls per car | B22: 60 | C22: USD | D22: INFERRED
A23: People per car | B23: 4 | C23: people | D23: assumption
A24: Included for everyone
A25: DAN cover inside the fee | B25: 0 | C25: USD | D25: George 24 Sep: not in the fee; each diver buys their own cover (see own spending)
A26: Hotel room-tax buffer per head | B26: 0 | C26: USD | D26: zero: the Nautilus rate is quoted tax-inclusive (30 Sep)
A27: Leader costs carried by the group
A28: George's flight allowance PHL–SJU | B28: 550 | C28: USD | D28: policy; Thanksgiving band 400–700
A29: George's half of a shared room | B29: =Inputs!$B$16*Inputs!$B$17/2 -> 353.4 | C29: USD | D29: formula
A30: Odd-headcount room risk | B30: =Inputs!$B$29 -> 353.4 | C30: USD | D30: half a room
A31: George's DAN carried by the group | B31: 0 | C31: USD | D31: George 24 Sep: own cost like everyone
A32: George's gear | B32: =Inputs!$B$11*Inputs!$B$10 -> 75 | C32: USD | D32: formula
A33: Own spending guidance (no flights)
A34: Meals and drinks per day (Thanksgiving dinner included) | B34: 45 | C34: USD/day | D34: INFERRED
A35: Days | B35: 4 | C35: days
A36: Tips | B36: 40 | C36: USD | D36: INFERRED
A37: Sunset Bio Bay Cruise, list price (optional add-on; eat, cruise, swim; discount and tax apply) | B37: 85 | C37: USD | D37: QUOTED 24 Sep
A38: Dive-accident cover, required, bought by each person | B38: 84 | C38: USD | D38: ADVERTISED: DAN membership 40 + Master 44

Sheet Fee
A1: Trip fee per certified diver, set at the pricing headcount (USD, 2 sharing)
B2: Certified diver
A3: Diving: three two-tank mornings, group discount, plus tax | B3: =ROUND(Inputs!$B$7*(1-Inputs!$B$8)*(1+Inputs!$B$9)*Inputs!$B$10,0) -> 412
A4: Gear rental, everyone | B4: =Inputs!$B$11*Inputs!$B$10 -> 75
A5: DAN dive-accident cover (not in the fee; each person buys their own, see below) | B5: =Inputs!$B$25 -> 0
A6: Hotel, 4 nights, 2 sharing | B6: =Inputs!$B$16*Inputs!$B$17/2 -> 353.4
A7: Hire cars, shared by everyone | B7: =(ROUNDUP(Inputs!$B$4/Inputs!$B$23,0)*(Inputs!$B$20*Inputs!$B$21+Inputs!$B$22))/(Inputs!$B$4-1) -> 136.66667
A8: Tax buffer | B8: =Inputs!$B$26 -> 0
A9: Leader's costs shared (George's flight, half-room, DAN, gear, odd-room risk) | B9: =(Inputs!$B$28+Inputs!$B$29+Inputs!$B$30+Inputs!$B$31+Inputs!$B$32)/(Inputs!$B$4-1) -> 147.97778
A10: Subtotal | B10: =SUM(B3:B9) -> 1125.0444
A11: Contingency | B11: =ROUND(B10*Inputs!$B$5,0) -> 68
A12: TRIP FEE (rounded up to the nearest 50) | B12: =CEILING(B10+B11,50) -> 1200
A14: Optional add-ons, charged at cost
A15: Sunset Bio Bay Cruise, after discount and tax | B15: =ROUND(Inputs!$B$37*(1-Inputs!$B$8)*(1+Inputs!$B$9),0) -> 81
A16: Night dive, after discount and tax, plus gear | B16: =ROUND(Inputs!$B$12*(1-Inputs!$B$8)*(1+Inputs!$B$9),0)+Inputs!$B$11 -> 158
A17: Third dive in the afternoon: not offered (air only); night dive Fri instead | B17: =Inputs!$B$13 -> 0
A19: GUIDANCE BUDGET WITHOUT FLIGHTS
A20: Trip fee | B20: =B12 -> 1200
A21: Own spending: dive cover, meals incl. Thanksgiving dinner, drinks, tips | B21: =Inputs!$B$38+Inputs!$B$34*Inputs!$B$35+Inputs!$B$36 -> 304
A22: Guidance budget | B22: =B20+B21 -> 1504
A23: Guidance budget with bio bay and night dive | B23: =B22+B15+B16 -> 1743

Sheet Group
A1: Group budget at three sizes (George leads and does not pay)
B2: 8 people (minimum) | C2: 10 people (pricing basis) | D2: 12 people (boat max)
A3: People including George | B3: 8 | C3: 10 | D3: 12
A4: Paying divers | B4: =B3-1 -> 7 | C4: =C3-1 -> 9 | D4: =D3-1 -> 11
A5: Rooms, 2 sharing (odd person alone at the group's cost) | B5: =ROUNDUP(B3/2,0) -> 4 | C5: =ROUNDUP(C3/2,0) -> 5 | D5: =ROUNDUP(D3/2,0) -> 6
A6: Hire cars | B6: =ROUNDUP(B3/Inputs!$B$23,0) -> 2 | C6: =ROUNDUP(C3/Inputs!$B$23,0) -> 3 | D6: =ROUNDUP(D3/Inputs!$B$23,0) -> 3
A7: Revenue
A8: Trip fees collected | B8: =B4*Fee!$B$12 -> 8400 | C8: =C4*Fee!$B$12 -> 10800 | D8: =D4*Fee!$B$12 -> 13200
A9: Costs
A10: Paradise Scuba: paying divers, three mornings, discount, tax (George free) | B10: =ROUND(B4*Inputs!$B$7*(1-Inputs!$B$8)*(1+Inputs!$B$9)*Inputs!$B$10,0) -> 2886 | C10: =ROUND(C4*Inputs!$B$7*(1-Inputs!$B$8)*(1+Inputs!$B$9)*Inputs!$B$10,0) -> 3710 | D10: =ROUND(D4*Inputs!$B$7*(1-Inputs!$B$8)*(1+Inputs!$B$9)*Inputs!$B$10,0) -> 4535
A11: Gear rental, everyone including George | B11: =B3*Inputs!$B$11*Inputs!$B$10 -> 600 | C11: =C3*Inputs!$B$11*Inputs!$B$10 -> 750 | D11: =D3*Inputs!$B$11*Inputs!$B$10 -> 900
A12: DAN for everyone including George | B12: =B3*Inputs!$B$25 -> 0 | C12: =C3*Inputs!$B$25 -> 0 | D12: =D3*Inputs!$B$25 -> 0
A13: Hotel block | B13: =B5*Inputs!$B$16*Inputs!$B$17 -> 2827.2 | C13: =C5*Inputs!$B$16*Inputs!$B$17 -> 3534 | D13: =D5*Inputs!$B$16*Inputs!$B$17 -> 4240.8
A14: Hire cars, fuel and tolls | B14: =B6*(Inputs!$B$20*Inputs!$B$21+Inputs!$B$22) -> 820 | C14: =C6*(Inputs!$B$20*Inputs!$B$21+Inputs!$B$22) -> 1230 | D14: =D6*(Inputs!$B$20*Inputs!$B$21+Inputs!$B$22) -> 1230
A15: Tax buffer held (paid if charged, else refunded) | B15: =B3*Inputs!$B$26 -> 0 | C15: =C3*Inputs!$B$26 -> 0 | D15: =D3*Inputs!$B$26 -> 0
A16: George's flight allowance | B16: =Inputs!$B$28 -> 550 | C16: =Inputs!$B$28 -> 550 | D16: =Inputs!$B$28 -> 550
A17: TOTAL COSTS | B17: =B10+B11+B12+B13+B14+B15+B16 -> 7683.2 | C17: =C10+C11+C12+C13+C14+C15+C16 -> 9774 | D17: =D10+D11+D12+D13+D14+D15+D16 -> 11455.8
A18: Result
A19: Surplus (contingency and over-recovery; refunded pro rata or held) | B19: =B8-B17 -> 716.8 | C19: =C8-C17 -> 1026 | D19: =D8-D17 -> 1744.2
A20: Covered? | B20: =IF(B19>=0,"yes","NO") -> yes | C20: =IF(C19>=0,"yes","NO") -> yes | D20: =IF(D19>=0,"yes","NO") -> yes
A21: Deposits and cash
A22: Participant deposits at sign-up (USD 400 each) | B22: =B4*400 -> 2800 | C22: =C4*400 -> 3600 | D22: =D4*400 -> 4400
A23: Paradise Scuba 50% deposit + hotel deposit | B23: =B10*Inputs!$B$14+B13*Inputs!$B$18 -> 2149.8 | C23: =C10*Inputs!$B$14+C13*Inputs!$B$18 -> 2738.5 | D23: =D10*Inputs!$B$14+D13*Inputs!$B$18 -> 3327.7
A24: Deposit cover (positive means deposits fund the outflow) | B24: =B22-B23 -> 650.2 | C24: =C22-C23 -> 861.5 | D24: =D22-D23 -> 1072.3
A25: Balances due from participants by Fri 23 Oct | B25: =B8-B22 -> 5600 | C25: =C8-C22 -> 7200 | D25: =D8-D22 -> 8800
A26: Paradise balance (by Mon 26 Oct, 30 days out) + hotel balance + gear + DAN + cars | B26: =B10*(1-Inputs!$B$14)+B13*(1-Inputs!$B$18)+B11+B12+B14 -> 4983.4 | C26: =C10*(1-Inputs!$B$14)+C13*(1-Inputs!$B$18)+C11+C12+C14 -> 6485.5 | D26: =D10*(1-Inputs!$B$14)+D13*(1-Inputs!$B$18)+D11+D12+D14 -> 7578.1
A27: Notes: no comps or commission are on offer here beyond George's free place, which Paradise Scuba quoted. If a cheaper hotel quote or a lower tax rate lands, rerun this builder.

Sheet Payments
A1: Payment schedule and refund policy (mirrors Paradise Scuba's terms)
A2: date | B2: what | C2: who
A3: by Fri 2 Oct | B3: Sign-ups open; USD 400 deposit holds a place; capacity 12 (one boat) | C3: participants
A4: Sat 10 Oct | B4: Sign-up deadline; headcount to Paradise Scuba and the hotel; cars booked | C4: George
A5: by Thu 15 Oct | B5: Paradise Scuba 50% deposit; hotel deposit | C5: club account
A6: Fri 23 Oct | B6: Participant balances due | C6: participants
A7: Mon 26 Oct | B7: Paradise Scuba balance (30 days out); hotel balance per its terms; DAN bought | C7: club account
A8: Mon 26 Oct | B8: Paradise Scuba's 30-day refund cut-off | C8: everyone
A9: Wed 25 Nov | B9: Fly PHL–SJU, drive to La Parguera | C9: everyone
A11: Refund ladder | B11: Deposit refundable in full until Fri 23 Oct; after 26 Oct only if the place is resold. Weather: Paradise reschedules or refunds missed dives (to confirm). | C11: policy
A12: Money handling | B12: CampusGroups or the operator's own link, never personal Venmo or Zelle. George's free place, flight allowance and half-room are disclosed on the sign-up page. | C12: policy
